targon/__init__.py
targon/version.py
targon/cli/__init__.py
targon/cli/app.py
targon/cli/auth.py
targon/cli/deploy.py
targon/cli/imports.py
targon/cli/inventory.py
targon/cli/main.py
targon/cli/run.py
targon/cli/setup.py
targon/client/app.py
targon/client/client.py
targon/client/constants.py
targon/client/functions.py
targon/client/heim.py
targon/client/inventory.py
targon/client/invocation.py
targon/client/publish.py
targon/core/app.py
targon/core/config.py
targon/core/console.py
targon/core/decorators.py
targon/core/exceptions.py
targon/core/executor.py
targon/core/function.py
targon/core/image.py
targon/core/objects.py
targon/core/partial_function.py
targon/core/resolver.py
targon/core/resources.py
targon/core/utils.py
targon/proto/__init__.py
targon/proto/function_execution_pb2.py
targon/proto/function_execution_pb2.pyi
targon/proto/function_execution_pb2_grpc.py
targon/runtime/__init__.py
targon/runtime/asgi.py
targon/runtime/runtime_init.py
targon/runtime/universal_runtime.py
targon_sdk-0.1.0.dist-info/licenses/LICENSE
targon_sdk-0.1.0.dist-info/METADATA
targon_sdk-0.1.0.dist-info/WHEEL
targon_sdk-0.1.0.dist-info/entry_points.txt
targon_sdk-0.1.0.dist-info/top_level.txt
targon_sdk-0.1.0.dist-info/RECORD
