Metadata-Version: 2.4
Name: targon-sdk
Version: 0.1.0
Summary: Targon sdk to interacte with the targon rentals and serverless
Author-email: Manifold Labs <dev@manifold.inc>
License:                                  Apache License
Keywords: api,sdk,targon
Requires-Python: >=3.9
License-File: LICENSE
Requires-Dist: requests>=2.28.0
Requires-Dist: click>=8.0.0
Requires-Dist: keyring==25.6.0
Requires-Dist: rich==14.1.0
Requires-Dist: aiohttp>=3.8.0
Requires-Dist: cloudpickle>=2.0.0
Requires-Dist: PyYAML>=6.0
Requires-Dist: grpcio>=1.60.0
Requires-Dist: grpcio-health-checking>=1.60.0
Requires-Dist: grpcio-tools>=1.60.0
Requires-Dist: protobuf>=4.25.0
Provides-Extra: dev
Requires-Dist: black>=24.0; extra == "dev"
Requires-Dist: flake8>=6.0; extra == "dev"
Requires-Dist: isort>=6.0; extra == "dev"
Requires-Dist: mypy>=1.5; extra == "dev"
Dynamic: license-file
